pet/__init__.py
pet/cli.py
pet/commands/__init__.py
pet/commands/init_command.py
pet/commands/list_workspace_command.py
pet/commands/login_command.py
pet/commands/pack_command.py
pet/commands/pull_command.py
pet/commands/push_command.py
pet/commands/run_command.py
pet/commands/validate_command.py
py_extension_toolkit-2.0.2.dist-info/licenses/LICENSE
py_extension_toolkit-2.0.2.dist-info/METADATA
py_extension_toolkit-2.0.2.dist-info/WHEEL
py_extension_toolkit-2.0.2.dist-info/entry_points.txt
py_extension_toolkit-2.0.2.dist-info/top_level.txt
py_extension_toolkit-2.0.2.dist-info/RECORD
