Metadata-Version: 2.4
Name: py-extension-toolkit
Version: 2.0.2
Summary: A Python CLI tool for creating web extensions, microservices, and integrations with ease
Home-page: https://github.com/Aqary-Org/py-extension-toolkit
Author: AQARY INTERNATIONAL GROUP
Author-email: Python Extension Toolkit Team <pet@example.com>
License-Expression: MIT
Project-URL: Homepage, https://github.com/Aqary-Org/py-extension-toolkit
Project-URL: Documentation, https://github.com/Aqary-Org/py-extension-toolkit#readme
Project-URL: Repository, https://github.com/Aqary-Org/py-extension-toolkit.git
Project-URL: Bug Tracker, https://github.com/Aqary-Org/py-extension-toolkit/issues
Keywords: cli,extension,development,toolkit,pet
Classifier: Development Status :: 5 - Production/Stable
Classifier: Intended Audience :: Developers
Classifier: Programming Language :: Python :: 3
Classifier: Programming Language :: Python :: 3.8
Classifier: Programming Language :: Python :: 3.9
Classifier: Programming Language :: Python :: 3.10
Classifier: Programming Language :: Python :: 3.11
Classifier: Programming Language :: Python :: 3.12
Classifier: Topic :: Software Development :: Libraries :: Python Modules
Classifier: Topic :: Software Development :: Build Tools
Requires-Python: >=3.7
License-File: LICENSE
Requires-Dist: click>=8.0.0
Requires-Dist: flask>=2.0.1
Requires-Dist: flask-cors>=4.0.0
Requires-Dist: requests>=2.25.0
Requires-Dist: questionary>=1.10.0
Provides-Extra: dev
Requires-Dist: pytest>=6.0; extra == "dev"
Requires-Dist: black; extra == "dev"
Requires-Dist: flake8; extra == "dev"
Dynamic: author
Dynamic: home-page
Dynamic: license-file
Dynamic: requires-python
